colors/__init__.py
colors/core.py
colors/main.py
random_color_otus-0.2.dist-info/METADATA
random_color_otus-0.2.dist-info/WHEEL
random_color_otus-0.2.dist-info/entry_points.txt
random_color_otus-0.2.dist-info/top_level.txt
random_color_otus-0.2.dist-info/RECORD
