Metadata-Version: 2.1
Name: random-color-otus
Version: 0.2
Summary: random colors
Home-page: https://github.com/DanteOnline/charon
Author: DanteOnline
Author-email: iamdanteonline@gmail.com
License: GNU General Public License v3.0
Keywords: iw,dev,trxpower,monitor,managed,interface,wi-fi
Platform: UNKNOWN
